gtx_mcp_server/__init__.py
gtx_mcp_server/__main__.py
gtx_mcp_server/config_demo.yml
gtx_mcp_server/database_env.py
gtx_mcp_server/local_model/README.md
gtx_mcp_server/local_model/local_xiyan_server.py
gtx_mcp_server/server.py
gtx_mcp_server/utils/common_util.py
gtx_mcp_server/utils/db_config.py
gtx_mcp_server/utils/db_mschema.py
gtx_mcp_server/utils/db_source.py
gtx_mcp_server/utils/db_util.py
gtx_mcp_server/utils/file_util.py
gtx_mcp_server/utils/llm_util.py
gtx_mcp_server/utils/logger_util.py
gtx_mcp_server-0.1.5.dev1.dist-info/WHEEL
gtx_mcp_server-0.1.5.dev1.dist-info/entry_points.txt
gtx_mcp_server-0.1.5.dev1.dist-info/METADATA
gtx_mcp_server-0.1.5.dev1.dist-info/RECORD
