Metadata-Version: 2.3
Name: gtx-mcp-server
Version: 0.1.5.dev1
Summary: A Model Context Protocol (MCP) server that utilizes XiyanSQL with databases. This server enables AI assistants to list tables, read data, and execute natural language queries
Author: Zhiling Luo
Author-email: Zhiling Luo <godot.lzl@alibaba-inc.com>
Requires-Dist: mcp>=1.0.0
Requires-Dist: mysql-connector-python>=9.1.0
Requires-Dist: llama-index
Requires-Dist: sqlalchemy
Requires-Dist: pymysql
Requires-Python: >=3.11
